CHANGELOG.rst
MANIFEST.in
README.rst
setup.py
src/interlude/__init__.py
src/interlude.egg-info/PKG-INFO
src/interlude.egg-info/SOURCES.txt
src/interlude.egg-info/dependency_links.txt
src/interlude.egg-info/namespace_packages.txt
src/interlude.egg-info/requires.txt
src/interlude.egg-info/top_level.txt
src/interlude.egg-info/zip-safe