Metadata-Version: 1.1
Name: interlude
Version: 1.2
Summary: Interlude for Doctests provides an Interactive Console.
Home-page: http://github.com/collective/interlude
Author: Jens Klein
Author-email: dev@bluedynamics.com
License: LGPL
Platform: UNKNOWN
Classifier: Development Status :: 6 - Mature
Classifier: Intended Audience :: Developers
Classifier: Operating System :: OS Independent
Classifier: Programming Language :: Python
Classifier: License :: OSI Approved :: GNU Library or Lesser General Public License (LGPL)
Classifier: Topic :: Software Development :: Libraries :: Python Modules
